odoo/addons/account_move_fiscal_month/README.rst
odoo/addons/account_move_fiscal_month/__init__.py
odoo/addons/account_move_fiscal_month/__manifest__.py
odoo/addons/account_move_fiscal_month/i18n/account_move_fiscal_month.pot
odoo/addons/account_move_fiscal_month/i18n/am.po
odoo/addons/account_move_fiscal_month/i18n/ca.po
odoo/addons/account_move_fiscal_month/i18n/de.po
odoo/addons/account_move_fiscal_month/i18n/es.po
odoo/addons/account_move_fiscal_month/i18n/es_EC.po
odoo/addons/account_move_fiscal_month/i18n/fr.po
odoo/addons/account_move_fiscal_month/i18n/gl.po
odoo/addons/account_move_fiscal_month/i18n/hr.po
odoo/addons/account_move_fiscal_month/i18n/hr_HR.po
odoo/addons/account_move_fiscal_month/i18n/it.po
odoo/addons/account_move_fiscal_month/i18n/nl.po
odoo/addons/account_move_fiscal_month/i18n/pt.po
odoo/addons/account_move_fiscal_month/i18n/pt_BR.po
odoo/addons/account_move_fiscal_month/i18n/pt_PT.po
odoo/addons/account_move_fiscal_month/i18n/sl.po
odoo/addons/account_move_fiscal_month/i18n/tr_TR.po
odoo/addons/account_move_fiscal_month/models/__init__.py
odoo/addons/account_move_fiscal_month/models/account_move.py
odoo/addons/account_move_fiscal_month/models/account_move_line.py
odoo/addons/account_move_fiscal_month/readme/CONFIGURE.rst
odoo/addons/account_move_fiscal_month/readme/CONTRIBUTORS.rst
odoo/addons/account_move_fiscal_month/readme/DESCRIPTION.rst
odoo/addons/account_move_fiscal_month/static/description/icon.png
odoo/addons/account_move_fiscal_month/static/description/index.html
odoo/addons/account_move_fiscal_month/tests/__init__.py
odoo/addons/account_move_fiscal_month/tests/test_account_move_fiscal_month.py
odoo/addons/account_move_fiscal_month/views/account_move.xml
odoo/addons/account_move_fiscal_month/views/account_move_line.xml
odoo14_addon_account_move_fiscal_month-14.0.1.0.1.dev8.dist-info/METADATA
odoo14_addon_account_move_fiscal_month-14.0.1.0.1.dev8.dist-info/WHEEL
odoo14_addon_account_move_fiscal_month-14.0.1.0.1.dev8.dist-info/top_level.txt
odoo14_addon_account_move_fiscal_month-14.0.1.0.1.dev8.dist-info/RECORD
