Metadata-Version: 2.1
Name: odoo14-addon-account_move_fiscal_month
Version: 14.0.1.0.1.dev8
Summary: Display the fiscal month on journal entries/item
Home-page: https://github.com/OCA/account-financial-tools
Author: ACSONE SA/NV,Odoo Community Association (OCA)
Author-email: support@odoo-community.org
License: AGPL-3
Classifier: Programming Language :: Python
Classifier: Framework :: Odoo
Classifier: Framework :: Odoo :: 14.0
Classifier: License :: OSI Approved :: GNU Affero General Public License v3
Requires-Python: >=3.6
Requires-Dist: odoo14-addon-account-fiscal-month
Requires-Dist: odoo<14.1dev,>=14.0a
